{"cookies": [], "origins": [{"origin": "https://nikita-filonov.github.io", "localStorage": [{"name": "persist:users", "value": "{\"user\":\"{\\\"id\\\":\\\"bea2a59c-38b2-4e60-9e98-164fc3c8c782\\\",\\\"email\\\":\\\"username@gmail@mail.ru\\\",\\\"username\\\":\\\"username\\\",\\\"password\\\":\\\"Password\\\"}\",\"users\":\"[{\\\"id\\\":\\\"bea2a59c-38b2-4e60-9e98-164fc3c8c782\\\",\\\"email\\\":\\\"username@gmail@mail.ru\\\",\\\"username\\\":\\\"username\\\",\\\"password\\\":\\\"Password\\\"}]\",\"_persist\":\"{\\\"version\\\":-1,\\\"rehydrated\\\":true}\"}"}, {"name": "persist:courses", "value": "{\"course\":\"{\\\"id\\\":\\\"\\\",\\\"title\\\":\\\"\\\",\\\"userId\\\":\\\"\\\",\\\"maxScore\\\":0,\\\"minScore\\\":0,\\\"exercises\\\":[],\\\"description\\\":\\\"\\\",\\\"previewImage\\\":null,\\\"estimatedTime\\\":\\\"\\\"}\",\"courses\":\"[]\",\"_persist\":\"{\\\"version\\\":-1,\\\"rehydrated\\\":true}\"}"}]}]}